section9_tools-0.0.2-py3.10-nspkg.pth
section9/epub_maker.py
section9/pic_maker.py
section9_tools-0.0.2.dist-info/LICENSE
section9_tools-0.0.2.dist-info/METADATA
section9_tools-0.0.2.dist-info/WHEEL
section9_tools-0.0.2.dist-info/entry_points.txt
section9_tools-0.0.2.dist-info/namespace_packages.txt
section9_tools-0.0.2.dist-info/top_level.txt
section9_tools-0.0.2.dist-info/RECORD
