Metadata-Version: 2.1
Name: section9-tools
Version: 0.0.2
Summary: section9 daily tools
Home-page: https://github.com/T-G-Family/section9-lib-tools
Author: sunyi00
Author-email: sunyi00@gmail.com
Project-URL: Bug Tracker, https://github.com/T-G-Family/section9-lib-tools/issues
Classifier: Programming Language :: Python :: 3
Classifier: License :: OSI Approved :: MIT License
Classifier: Operating System :: OS Independent
Requires-Python: >=3.8
License-File: LICENSE
Requires-Dist: arrow
Requires-Dist: requests
Requires-Dist: EbookLib
Requires-Dist: Faker
Requires-Dist: pillow
Requires-Dist: streamlit
Requires-Dist: watchdog
Requires-Dist: colorthief
Requires-Dist: opencv-python
Requires-Dist: imagehash
Requires-Dist: fire
Provides-Extra: dev
Requires-Dist: pip-tools ; extra == 'dev'
Requires-Dist: build ; extra == 'dev'
Requires-Dist: twine ; extra == 'dev'
Provides-Extra: test
Requires-Dist: pytest ; extra == 'test'
Requires-Dist: pytest-mock ; extra == 'test'
Requires-Dist: pytest-cov ; extra == 'test'
Requires-Dist: black ; extra == 'test'
Requires-Dist: coverage ; extra == 'test'
Requires-Dist: flake8 ; extra == 'test'
Requires-Dist: mypy ; extra == 'test'
Requires-Dist: ipython ; extra == 'test'
Requires-Dist: pynvim ; extra == 'test'
Requires-Dist: pylint ; extra == 'test'
Requires-Dist: isort ; extra == 'test'
Requires-Dist: pipdeptree ; extra == 'test'
Requires-Dist: pep8 ; extra == 'test'
Requires-Dist: autopep8 ; extra == 'test'
